formancesdkflows/__init__.py
formancesdkflows/instances.py
formancesdkflows/sdk.py
formancesdkflows/sdkconfiguration.py
formancesdkflows/triggers.py
formancesdkflows/workflows.py
formancesdkflows/_hooks/__init__.py
formancesdkflows/_hooks/clientcredentials.py
formancesdkflows/_hooks/registration.py
formancesdkflows/_hooks/sdkhooks.py
formancesdkflows/_hooks/types.py
formancesdkflows/models/__init__.py
formancesdkflows/models/components/__init__.py
formancesdkflows/models/components/flowerrors.py
formancesdkflows/models/components/ledger_account.py
formancesdkflows/models/components/ledger_createtransactionwithnumscript.py
formancesdkflows/models/components/ledger_createtransactionwithpostings.py
formancesdkflows/models/components/ledger_posting.py
formancesdkflows/models/components/ledger_transaction.py
formancesdkflows/models/components/ledger_volume.py
formancesdkflows/models/components/payments_connector.py
formancesdkflows/models/components/payments_payment.py
formancesdkflows/models/components/payments_paymentadjustment.py
formancesdkflows/models/components/payments_paymentscheme.py
formancesdkflows/models/components/payments_paymentstatus.py
formancesdkflows/models/components/payments_paymenttype.py
formancesdkflows/models/components/schemeformanceoauth.py
formancesdkflows/models/components/security.py
formancesdkflows/models/components/serverinfo.py
formancesdkflows/models/components/stagedelay.py
formancesdkflows/models/components/stagesend.py
formancesdkflows/models/components/stagewaitevent.py
formancesdkflows/models/components/trigger.py
formancesdkflows/models/components/triggeroccurence.py
formancesdkflows/models/components/triggertest.py
formancesdkflows/models/components/walletcounterpart.py
formancesdkflows/models/components/wallets_creditwalletinput.py
formancesdkflows/models/components/wallets_debitwalletinput.py
formancesdkflows/models/components/wallets_hold.py
formancesdkflows/models/components/wallets_wallet.py
formance_sdk_flows-1.0.0a12.dist-info/METADATA
formance_sdk_flows-1.0.0a12.dist-info/WHEEL
formance_sdk_flows-1.0.0a12.dist-info/top_level.txt
formance_sdk_flows-1.0.0a12.dist-info/RECORD
